windows_sandbox_manager/__init__.py
windows_sandbox_manager/exceptions.py
windows_sandbox_manager/cli/__init__.py
windows_sandbox_manager/cli/main.py
windows_sandbox_manager/config/__init__.py
windows_sandbox_manager/config/models.py
windows_sandbox_manager/core/__init__.py
windows_sandbox_manager/core/manager.py
windows_sandbox_manager/core/registry.py
windows_sandbox_manager/core/sandbox.py
windows_sandbox_manager/monitoring/__init__.py
windows_sandbox_manager/monitoring/resources.py
windows_sandbox_manager/security/__init__.py
windows_sandbox_manager/security/validation.py
windows_sandbox_manager/utils/__init__.py
windows_sandbox_manager/utils/system_check.py
windows_sandbox_manager/utils/windows.py
windows_sandbox_manager-0.3.1.dist-info/METADATA
windows_sandbox_manager-0.3.1.dist-info/WHEEL
windows_sandbox_manager-0.3.1.dist-info/entry_points.txt
windows_sandbox_manager-0.3.1.dist-info/licenses/LICENSE
windows_sandbox_manager-0.3.1.dist-info/RECORD
