Metadata-Version: 2.4
Name: windows-sandbox-manager
Version: 0.3.1
Summary: A modern, secure, and scalable Python library for creating and managing Windows Sandbox instances
Project-URL: Homepage, https://github.com/Amal-David/python-windows-sandbox
Project-URL: Documentation, https://python-windows-sandbox.readthedocs.io
Project-URL: Repository, https://github.com/Amal-David/python-windows-sandbox
Project-URL: Bug Tracker, https://github.com/Amal-David/python-windows-sandbox/issues
Project-URL: Changelog, https://github.com/Amal-David/python-windows-sandbox/blob/main/CHANGELOG.md
Author-email: Amal David <labuka@duck.com>
License-Expression: MIT
License-File: LICENSE
Keywords: isolation,sandbox,security,virtualization,windows
Classifier: Development Status :: 4 - Beta
Classifier: Intended Audience :: Developers
Classifier: License :: OSI Approved :: MIT License
Classifier: Operating System :: Microsoft :: Windows
Classifier: Programming Language :: Python :: 3
Classifier: Programming Language :: Python :: 3.9
Classifier: Programming Language :: Python :: 3.10
Classifier: Programming Language :: Python :: 3.11
Classifier: Programming Language :: Python :: 3.12
Classifier: Topic :: Security
Classifier: Topic :: Software Development :: Libraries :: Python Modules
Classifier: Topic :: System :: Operating System
Requires-Python: >=3.9
Requires-Dist: aiofiles>=23.0.0
Requires-Dist: click>=8.0.0
Requires-Dist: grpcio-tools>=1.54.0
Requires-Dist: grpcio>=1.54.0
Requires-Dist: prometheus-client>=0.16.0
Requires-Dist: protobuf>=4.21.0
Requires-Dist: psutil>=5.9.0
Requires-Dist: pydantic>=2.0.0
Requires-Dist: pyyaml>=6.0
Requires-Dist: rich>=13.0.0
Requires-Dist: structlog>=23.0.0
Requires-Dist: typing-extensions>=4.5.0
Provides-Extra: dev
Requires-Dist: black>=23.0.0; extra == 'dev'
Requires-Dist: coverage[toml]>=7.0.0; extra == 'dev'
Requires-Dist: flake8>=6.0.0; extra == 'dev'
Requires-Dist: isort>=5.12.0; extra == 'dev'
Requires-Dist: mypy>=1.0.0; extra == 'dev'
Requires-Dist: pre-commit>=3.0.0; extra == 'dev'
Requires-Dist: pytest-asyncio>=0.21.0; extra == 'dev'
Requires-Dist: pytest-cov>=4.0.0; extra == 'dev'
Requires-Dist: pytest-mock>=3.10.0; extra == 'dev'
Requires-Dist: pytest>=7.0.0; extra == 'dev'
Requires-Dist: tox>=4.0.0; extra == 'dev'
Requires-Dist: types-pyyaml>=6.0.0; extra == 'dev'
Provides-Extra: docs
Requires-Dist: mkdocs-material>=9.0.0; extra == 'docs'
Requires-Dist: mkdocs>=1.4.0; extra == 'docs'
Requires-Dist: mkdocstrings[python]>=0.20.0; extra == 'docs'
Provides-Extra: test
Requires-Dist: pytest-asyncio>=0.21.0; extra == 'test'
Requires-Dist: pytest-cov>=4.0.0; extra == 'test'
Requires-Dist: pytest-mock>=3.10.0; extra == 'test'
Requires-Dist: pytest>=7.0.0; extra == 'test'
